[
  {
    "type": "tree",
    "data": {
      "id": "polski-matura-mini",
      "title": "Polski — matura (mini)",
      "branches": "{\"epoki\": {\"label\": \"Epoki\", \"color\": \"primary\"}, \"lektury\": {\"label\": \"Lektury\", \"color\": \"info\"}}",
      "edges": "[{\"from\": \"antyk\", \"to\": \"sredniowiecze\", \"type\": \"progression\"}, {\"from\": \"sredniowiecze\", \"to\": \"renesans\", \"type\": \"progression\"}, {\"from\": \"renesans\", \"to\": \"barok\", \"type\": \"progression\"}, {\"from\": \"barok\", \"to\": \"oswiecenie\", \"type\": \"progression\"}, {\"from\": \"oswiecenie\", \"to\": \"romantyzm\", \"type\": \"progression\"}, {\"from\": \"romantyzm\", \"to\": \"pozytywizm\", \"type\": \"progression\"}, {\"from\": \"pozytywizm\", \"to\": \"mloda-polska\", \"type\": \"progression\"}, {\"from\": \"mloda-polska\", \"to\": \"miedzywojnie\", \"type\": \"progression\"}, {\"from\": \"miedzywojnie\", \"to\": \"wspolczesnosc\", \"type\": \"progression\"}, {\"from\": \"antyk\", \"to\": \"antygona\", \"type\": \"branch\"}, {\"from\": \"antyk\", \"to\": \"iliada\", \"type\": \"branch\"}, {\"from\": \"sredniowiecze\", \"to\": \"bogurodzica\", \"type\": \"branch\"}, {\"from\": \"renesans\", \"to\": \"makbet\", \"type\": \"branch\"}, {\"from\": \"oswiecenie\", \"to\": \"bajki\", \"type\": \"branch\"}, {\"from\": \"romantyzm\", \"to\": \"dziady3\", \"type\": \"branch\"}, {\"from\": \"pozytywizm\", \"to\": \"lalka\", \"type\": \"branch\"}, {\"from\": \"mloda-polska\", \"to\": \"wesele\", \"type\": \"branch\"}, {\"from\": \"miedzywojnie\", \"to\": \"granica\", \"type\": \"branch\"}, {\"from\": \"wspolczesnosc\", \"to\": \"dzuma\", \"type\": \"branch\"}]",
      "relations": "{\"progression\": {\"label\": \"Następstwo\", \"color\": \"info\"}, \"branch\": {\"label\": \"Należy do\", \"color\": \"primary\"}, \"kontekst\": {\"label\": \"Kontekst\", \"color\": \"warning\"}, \"postac\": {\"label\": \"Postać\", \"color\": \"secondary\"}}"
    },
    "children": [
      {
        "type": "node",
        "data": {
          "nodeId": "antyk",
          "title": "Antyk",
          "branch": "epoki",
          "tier": 0,
          "hits": 0
        }
      },
      {
        "type": "node",
        "data": {
          "nodeId": "sredniowiecze",
          "title": "Średniowiecze",
          "branch": "epoki",
          "tier": 1,
          "hits": 0
        }
      },
      {
        "type": "node",
        "data": {
          "nodeId": "renesans",
          "title": "Renesans",
          "branch": "epoki",
          "tier": 2,
          "hits": 0
        }
      },
      {
        "type": "node",
        "data": {
          "nodeId": "barok",
          "title": "Barok",
          "branch": "epoki",
          "tier": 3,
          "hits": 0
        }
      },
      {
        "type": "node",
        "data": {
          "nodeId": "oswiecenie",
          "title": "Oświecenie",
          "branch": "epoki",
          "tier": 4,
          "hits": 0
        }
      },
      {
        "type": "node",
        "data": {
          "nodeId": "romantyzm",
          "title": "Romantyzm",
          "branch": "epoki",
          "tier": 5,
          "hits": 0
        }
      },
      {
        "type": "node",
        "data": {
          "nodeId": "pozytywizm",
          "title": "Pozytywizm",
          "branch": "epoki",
          "tier": 6,
          "hits": 0
        }
      },
      {
        "type": "node",
        "data": {
          "nodeId": "mloda-polska",
          "title": "Młoda Polska",
          "branch": "epoki",
          "tier": 7,
          "hits": 0
        }
      },
      {
        "type": "node",
        "data": {
          "nodeId": "miedzywojnie",
          "title": "Międzywojnie",
          "branch": "epoki",
          "tier": 8,
          "hits": 0
        }
      },
      {
        "type": "node",
        "data": {
          "nodeId": "wspolczesnosc",
          "title": "Współczesność",
          "branch": "epoki",
          "tier": 9,
          "hits": 0
        }
      },
      {
        "type": "node",
        "data": {
          "nodeId": "antygona",
          "title": "Antygona",
          "branch": "lektury",
          "tier": 0,
          "hits": 0
        }
      },
      {
        "type": "node",
        "data": {
          "nodeId": "iliada",
          "title": "Iliada",
          "branch": "lektury",
          "tier": 1,
          "hits": 0
        }
      },
      {
        "type": "node",
        "data": {
          "nodeId": "bogurodzica",
          "title": "Bogurodzica",
          "branch": "lektury",
          "tier": 0,
          "hits": 0
        }
      },
      {
        "type": "node",
        "data": {
          "nodeId": "makbet",
          "title": "Makbet",
          "branch": "lektury",
          "tier": 0,
          "hits": 0
        }
      },
      {
        "type": "node",
        "data": {
          "nodeId": "bajki",
          "title": "Bajki",
          "branch": "lektury",
          "tier": 0,
          "hits": 0
        }
      },
      {
        "type": "node",
        "data": {
          "nodeId": "dziady3",
          "title": "Dziady cz. III",
          "branch": "lektury",
          "tier": 0,
          "hits": 0
        }
      },
      {
        "type": "node",
        "data": {
          "nodeId": "lalka",
          "title": "Lalka",
          "branch": "lektury",
          "tier": 0,
          "hits": 0
        }
      },
      {
        "type": "node",
        "data": {
          "nodeId": "wesele",
          "title": "Wesele",
          "branch": "lektury",
          "tier": 0,
          "hits": 0
        }
      },
      {
        "type": "node",
        "data": {
          "nodeId": "granica",
          "title": "Granica",
          "branch": "lektury",
          "tier": 0,
          "hits": 0
        }
      },
      {
        "type": "node",
        "data": {
          "nodeId": "dzuma",
          "title": "Dżuma",
          "branch": "lektury",
          "tier": 0,
          "hits": 0
        }
      }
    ]
  }
]
